jwst_reffiles/__init__.py
jwst_reffiles/mkref.py
jwst_reffiles/mkrefs.py
jwst_reffiles/plugin_wrapper.py
jwst_reffiles/bad_pixel_mask/__init__.py
jwst_reffiles/bad_pixel_mask/bad_pixel_mask.py
jwst_reffiles/bad_pixel_mask/badpix_from_flats.py
jwst_reffiles/bad_pixel_mask/fgs_guider1_manual_flags.txt
jwst_reffiles/bad_pixel_mask/fgs_guider2_manual_flags.txt
jwst_reffiles/bad_pixel_mask/miri_mirifulong_manual_flags.txt
jwst_reffiles/bad_pixel_mask/miri_mirifushort_manual_flags.txt
jwst_reffiles/bad_pixel_mask/miri_mirimage_manual_flags.txt
jwst_reffiles/bad_pixel_mask/mkref_bad_pixel_mask.py
jwst_reffiles/bad_pixel_mask/mkref_badpix_from_flats.py
jwst_reffiles/bad_pixel_mask/nircam_nrca1_manual_flags.txt
jwst_reffiles/bad_pixel_mask/nircam_nrca2_manual_flags.txt
jwst_reffiles/bad_pixel_mask/nircam_nrca3_manual_flags.txt
jwst_reffiles/bad_pixel_mask/nircam_nrca4_manual_flags.txt
jwst_reffiles/bad_pixel_mask/nircam_nrcalong_manual_flags.txt
jwst_reffiles/bad_pixel_mask/nircam_nrcb1_manual_flags.txt
jwst_reffiles/bad_pixel_mask/nircam_nrcb2_manual_flags.txt
jwst_reffiles/bad_pixel_mask/nircam_nrcb3_manual_flags.txt
jwst_reffiles/bad_pixel_mask/nircam_nrcb4_manual_flags.txt
jwst_reffiles/bad_pixel_mask/nircam_nrcblong_manual_flags.txt
jwst_reffiles/bad_pixel_mask/niriss_nis_manual_flags.txt
jwst_reffiles/bad_pixel_mask/nirspec_nrs1_manual_flags.txt
jwst_reffiles/bad_pixel_mask/nirspec_nrs2_manual_flags.txt
jwst_reffiles/dark_current/__init__.py
jwst_reffiles/dark_current/badpix_from_darks.py
jwst_reffiles/dark_current/dark_reffile.py
jwst_reffiles/dark_current/mkref_dark.py
jwst_reffiles/flat_field/__init__.py
jwst_reffiles/gain/__init__.py
jwst_reffiles/ipc/__init__.py
jwst_reffiles/linearity/__init__.py
jwst_reffiles/pipeline/__init__.py
jwst_reffiles/pipeline/calib_prep.py
jwst_reffiles/pipeline/find_file.py
jwst_reffiles/pipeline/pipeline_steps.py
jwst_reffiles/readnoise/__init__.py
jwst_reffiles/readnoise/mkref_readnoise.py
jwst_reffiles/readnoise/readnoise.py
jwst_reffiles-1.0.1.dist-info/LICENSE.txt
jwst_reffiles-1.0.1.dist-info/METADATA
jwst_reffiles-1.0.1.dist-info/WHEEL
jwst_reffiles-1.0.1.dist-info/entry_points.txt
jwst_reffiles-1.0.1.dist-info/top_level.txt
jwst_reffiles-1.0.1.dist-info/RECORD
