Metadata-Version: 2.1
Name: jwst_reffiles
Version: 1.0.1
Summary: A tool to create CRDS-formatted reference files for JWST from a set of input dark current files and a set of flat field files.
Author-email: "STScI (Rest, Hilbert, Canipe, et al.)" <arest@stsci.edu>
License: BSD-3-Clause
Classifier: Intended Audience :: Science/Research
Classifier: License :: OSI Approved :: BSD License
Classifier: Operating System :: OS Independent
Classifier: Programming Language :: Python
Classifier: Topic :: Scientific/Engineering :: Astronomy
Classifier: Topic :: Software Development :: Libraries :: Python Modules
Requires-Python: >=3.8
License-File: LICENSE.txt
Requires-Dist: astropy >=4.0
Requires-Dist: jwst
Requires-Dist: numpy >=1.16
Requires-Dist: matplotlib >=1.4.3
Requires-Dist: scipy >=1.1
Provides-Extra: docs
Requires-Dist: nbsphinx ; extra == 'docs'
Requires-Dist: ipykernel ; extra == 'docs'
Requires-Dist: sphinx ; extra == 'docs'
Requires-Dist: sphinx-rtd-theme ; extra == 'docs'
Provides-Extra: test
Requires-Dist: pytest ; extra == 'test'
